bilde-0.2.2.dist-info/WHEEL
bilde-0.2.2.dist-info/LICENSE
bilde-0.2.2.dist-info/METADATA
bilde-0.2.2.dist-info/RECORD
bilde-0.2.2.dist-info/top_level.txt
pybilde/bilde.cpython-313-i386-linux-gnu.so
pybilde/__init__.py
