Metadata-Version: 2.1
Name: bilde
Version: 0.2.2
Summary: A python version of the Bilde library
Home-page: https://github.com/anguelos/bilde
Author: Anguelos Nicolaou
Author-email: anguelos.nicolaou@gmail.com
Classifier: Programming Language :: Python :: 3
Classifier: Programming Language :: C++
Classifier: License :: OSI Approved :: MIT License
Classifier: Operating System :: OS Independent
Requires-Python: >=3.6
License-File: LICENSE
Requires-Dist: numpy
